{
  "success": true,
  "lastUpdated": 1768316459294,
  "totalServers": 47221,
  "totalPlayers": 163320,
  "resources": {
    "mnr_cayo": {
      "serverRank": 888,
      "playerRank": 1345,
      "serverRankChange": -1,
      "playerRankChange": 236,
      "servers": 957,
      "players": 3805
    },
    "mnr_postals": {
      "serverRank": 5545,
      "playerRank": 18085,
      "serverRankChange": -84,
      "playerRankChange": -7725,
      "servers": 198,
      "players": 515
    },
    "mnr_sitanywhere": {
      "serverRank": 14725,
      "playerRank": 37536,
      "serverRankChange": -151,
      "playerRankChange": -22372,
      "servers": 78,
      "players": 247
    },
    "mnr_fuel": {
      "serverRank": 30613,
      "playerRank": 52137,
      "serverRankChange": -1104,
      "playerRankChange": -18777,
      "servers": 35,
      "players": 160
    },
    "mnr_elevators": {
      "serverRank": 27404,
      "playerRank": 58516,
      "serverRankChange": -731,
      "playerRankChange": 53689,
      "servers": 40,
      "players": 135
    },
    "mnr_blips": {
      "serverRank": 47243,
      "playerRank": 143038,
      "serverRankChange": 508,
      "playerRankChange": 8887,
      "servers": 21,
      "players": 34
    },
    "mnr_showid": {
      "serverRank": 118604,
      "playerRank": 306482,
      "serverRankChange": -3391,
      "playerRankChange": -185550,
      "servers": 6,
      "players": 4
    },
    "mnr_ipl": {
      "serverRank": 87730,
      "playerRank": 170224,
      "serverRankChange": 9791,
      "playerRankChange": 88918,
      "servers": 9,
      "players": 23
    },
    "mnr_anticl": {
      "serverRank": 120635,
      "playerRank": 365195,
      "serverRankChange": -3739,
      "playerRankChange": -168628,
      "servers": 6,
      "players": 2
    },
    "mnr_zones": {
      "serverRank": 139600,
      "playerRank": 424282,
      "serverRankChange": 316,
      "playerRankChange": -12656,
      "servers": 5,
      "players": 1
    },
    "mnr_consumables": {
      "serverRank": 416064,
      "playerRank": 669000,
      "serverRankChange": 7843,
      "playerRankChange": 38669,
      "servers": 2,
      "players": 0
    },
    "mnr_dispatch": {
      "serverRank": 1027123,
      "playerRank": 1027123,
      "serverRankChange": 20094,
      "playerRankChange": 20094,
      "servers": 1,
      "players": 0
    },
    "mnr_loadingscreen": {
      "serverRank": 1027125,
      "playerRank": 1027125,
      "serverRankChange": 20095,
      "playerRankChange": 20095,
      "servers": 1,
      "players": 0
    }
  }
}