{
  "success": true,
  "lastUpdated": 1778828458661,
  "totalServers": 41572,
  "totalPlayers": 82482,
  "resources": {
    "mnr_cayo": {
      "serverRank": 486,
      "playerRank": 702,
      "serverRankChange": 0,
      "playerRankChange": 154,
      "servers": 1277,
      "players": 3307
    },
    "mnr_postals": {
      "serverRank": 4719,
      "playerRank": 12485,
      "serverRankChange": -5,
      "playerRankChange": 822,
      "servers": 173,
      "players": 299
    },
    "mnr_sitanywhere": {
      "serverRank": 9581,
      "playerRank": 53095,
      "serverRankChange": 41,
      "playerRankChange": -30546,
      "servers": 88,
      "players": 65
    },
    "mnr_fuel": {
      "serverRank": 36926,
      "playerRank": 135345,
      "serverRankChange": -188,
      "playerRankChange": -66826,
      "servers": 21,
      "players": 10
    },
    "mnr_elevators": {
      "serverRank": 23689,
      "playerRank": 103767,
      "serverRankChange": -392,
      "playerRankChange": 18555,
      "servers": 35,
      "players": 18
    },
    "mnr_blips": {
      "serverRank": 165438,
      "playerRank": 234128,
      "serverRankChange": -34947,
      "playerRankChange": 10937,
      "servers": 3,
      "players": 2
    },
    "mnr_showid": {
      "serverRank": 149350,
      "playerRank": 55381,
      "serverRankChange": 9987,
      "playerRankChange": 90793,
      "servers": 3,
      "players": 62
    },
    "mnr_ipl": {
      "serverRank": 89993,
      "playerRank": 355138,
      "serverRankChange": -3146,
      "playerRankChange": -132762,
      "servers": 7,
      "players": 0
    },
    "mnr_anticl": {
      "serverRank": 835326,
      "playerRank": 835326,
      "serverRankChange": 27485,
      "playerRankChange": 27485,
      "servers": 1,
      "players": 0
    },
    "mnr_zones": {
      "serverRank": 334972,
      "playerRank": 459259,
      "serverRankChange": 10649,
      "playerRankChange": 62670,
      "servers": 2,
      "players": 0
    },
    "mnr_consumables": {
      "serverRank": 835332,
      "playerRank": 835332,
      "serverRankChange": 27485,
      "playerRankChange": 27485,
      "servers": 1,
      "players": 0
    },
    "mnr_dispatch": {
      "serverRank": 187919,
      "playerRank": 392958,
      "serverRankChange": 4272,
      "playerRankChange": 75127,
      "servers": 3,
      "players": 0
    },
    "mnr_loadingscreen": {
      "serverRank": 835336,
      "playerRank": 835336,
      "serverRankChange": 27485,
      "playerRankChange": 27485,
      "servers": 1,
      "players": 0
    },
    "mnr_minimap": {
      "serverRank": 19064,
      "playerRank": 31070,
      "serverRankChange": -237,
      "playerRankChange": 15783,
      "servers": 44,
      "players": 135
    }
  }
}