{
  "success": true,
  "lastUpdated": 1776366054284,
  "totalServers": 41292,
  "totalPlayers": 216924,
  "resources": {
    "mnr_cayo": {
      "serverRank": 524,
      "playerRank": 811,
      "serverRankChange": 1,
      "playerRankChange": 111,
      "servers": 1210,
      "players": 6916
    },
    "mnr_postals": {
      "serverRank": 4549,
      "playerRank": 13602,
      "serverRankChange": -16,
      "playerRankChange": -3568,
      "servers": 177,
      "players": 660
    },
    "mnr_sitanywhere": {
      "serverRank": 9576,
      "playerRank": 14806,
      "serverRankChange": 175,
      "playerRankChange": -2152,
      "servers": 88,
      "players": 621
    },
    "mnr_fuel": {
      "serverRank": 28405,
      "playerRank": 42008,
      "serverRankChange": 570,
      "playerRankChange": -6941,
      "servers": 28,
      "players": 225
    },
    "mnr_elevators": {
      "serverRank": 17616,
      "playerRank": 104000,
      "serverRankChange": 407,
      "playerRankChange": 10531,
      "servers": 48,
      "players": 69
    },
    "mnr_blips": {
      "serverRank": 99508,
      "playerRank": 388520,
      "serverRankChange": -3013,
      "playerRankChange": -163117,
      "servers": 6,
      "players": 1
    },
    "mnr_showid": {
      "serverRank": 125146,
      "playerRank": 165698,
      "serverRankChange": -651,
      "playerRankChange": -50778,
      "servers": 4,
      "players": 27
    },
    "mnr_ipl": {
      "serverRank": 77270,
      "playerRank": 210247,
      "serverRankChange": -3348,
      "playerRankChange": 102060,
      "servers": 8,
      "players": 14
    },
    "mnr_anticl": {
      "serverRank": 127272,
      "playerRank": 220134,
      "serverRankChange": 2237,
      "playerRankChange": 14979,
      "servers": 4,
      "players": 12
    },
    "mnr_zones": {
      "serverRank": 860458,
      "playerRank": 860458,
      "serverRankChange": -2489,
      "playerRankChange": -2489,
      "servers": 1,
      "players": 0
    },
    "mnr_consumables": {
      "serverRank": 860448,
      "playerRank": 860448,
      "serverRankChange": -2490,
      "playerRankChange": -2490,
      "servers": 1,
      "players": 0
    },
    "mnr_dispatch": {
      "serverRank": 345239,
      "playerRank": 553241,
      "serverRankChange": 512721,
      "playerRankChange": 304719,
      "servers": 2,
      "players": 0
    },
    "mnr_loadingscreen": {
      "serverRank": 860451,
      "playerRank": 860451,
      "serverRankChange": -2489,
      "playerRankChange": -2489,
      "servers": 1,
      "players": 0
    },
    "mnr_minimap": {
      "serverRank": 22236,
      "playerRank": 51055,
      "serverRankChange": 591,
      "playerRankChange": 26270,
      "servers": 37,
      "players": 183
    }
  }
}