{
  "success": true,
  "lastUpdated": 1781283622633,
  "totalServers": 39692,
  "totalPlayers": 185179,
  "resources": {
    "mnr_cayo": {
      "serverRank": 459,
      "playerRank": 510,
      "serverRankChange": 1,
      "playerRankChange": 233,
      "servers": 1303,
      "players": 7940
    },
    "mnr_postals": {
      "serverRank": 4672,
      "playerRank": 18703,
      "serverRankChange": -115,
      "playerRankChange": -3957,
      "servers": 172,
      "players": 486
    },
    "mnr_sitanywhere": {
      "serverRank": 9067,
      "playerRank": 20374,
      "serverRankChange": -92,
      "playerRankChange": 18637,
      "servers": 91,
      "players": 433
    },
    "mnr_fuel": {
      "serverRank": 41395,
      "playerRank": 60725,
      "serverRankChange": -364,
      "playerRankChange": 31218,
      "servers": 18,
      "players": 124
    },
    "mnr_elevators": {
      "serverRank": 21604,
      "playerRank": 57871,
      "serverRankChange": 1477,
      "playerRankChange": 41409,
      "servers": 38,
      "players": 131
    },
    "mnr_blips": {
      "serverRank": 116593,
      "playerRank": 484485,
      "serverRankChange": 16688,
      "playerRankChange": -137848,
      "servers": 5,
      "players": 0
    },
    "mnr_showid": {
      "serverRank": 167575,
      "playerRank": 259158,
      "serverRankChange": -44436,
      "playerRankChange": -132199,
      "servers": 3,
      "players": 5
    },
    "mnr_ipl": {
      "serverRank": 113424,
      "playerRank": 369092,
      "serverRankChange": 2204,
      "playerRankChange": 71238,
      "servers": 5,
      "players": 1
    },
    "mnr_anticl": {
      "serverRank": 547942,
      "playerRank": 441741,
      "serverRankChange": 307622,
      "playerRankChange": 413823,
      "servers": 1,
      "players": 1
    },
    "mnr_zones": {
      "serverRank": 298580,
      "playerRank": 390833,
      "serverRankChange": 39694,
      "playerRankChange": 123461,
      "servers": 2,
      "players": 1
    },
    "mnr_consumables": {
      "serverRank": 547944,
      "playerRank": 441743,
      "serverRankChange": 307627,
      "playerRankChange": 413828,
      "servers": 1,
      "players": 1
    },
    "mnr_dispatch": {
      "serverRank": 298578,
      "playerRank": 390831,
      "serverRankChange": 39694,
      "playerRankChange": 123461,
      "servers": 2,
      "players": 1
    },
    "mnr_loadingscreen": {
      "serverRank": 298579,
      "playerRank": 390832,
      "serverRankChange": 556996,
      "playerRankChange": 464743,
      "servers": 2,
      "players": 1
    },
    "mnr_minimap": {
      "serverRank": 18754,
      "playerRank": 33240,
      "serverRankChange": 136,
      "playerRankChange": 7734,
      "servers": 44,
      "players": 257
    }
  }
}