{
  "success": true,
  "lastUpdated": 1783710032201,
  "totalServers": 21328,
  "totalPlayers": 150325,
  "resources": {
    "mnr_cayo": {
      "serverRank": 462,
      "playerRank": 595,
      "serverRankChange": -3,
      "playerRankChange": 68,
      "servers": 887,
      "players": 6509
    },
    "mnr_postals": {
      "serverRank": 4645,
      "playerRank": 15975,
      "serverRankChange": -78,
      "playerRankChange": -1962,
      "servers": 113,
      "players": 439
    },
    "mnr_sitanywhere": {
      "serverRank": 7235,
      "playerRank": 14600,
      "serverRankChange": 245,
      "playerRankChange": 25185,
      "servers": 72,
      "players": 490
    },
    "mnr_fuel": {
      "serverRank": 33146,
      "playerRank": 134052,
      "serverRankChange": 400,
      "playerRankChange": 12887,
      "servers": 15,
      "players": 25
    },
    "mnr_elevators": {
      "serverRank": 18683,
      "playerRank": 99417,
      "serverRankChange": 180,
      "playerRankChange": -15634,
      "servers": 28,
      "players": 47
    },
    "mnr_blips": {
      "serverRank": 104000,
      "playerRank": 387603,
      "serverRankChange": 195,
      "playerRankChange": -24527,
      "servers": 4,
      "players": 0
    },
    "mnr_showid": {
      "serverRank": 118601,
      "playerRank": 149666,
      "serverRankChange": -2575,
      "playerRankChange": -30276,
      "servers": 3,
      "players": 19
    },
    "mnr_ipl": {
      "serverRank": 129273,
      "playerRank": 279355,
      "serverRankChange": 11234,
      "playerRankChange": 93114,
      "servers": 3,
      "players": 2
    },
    "mnr_anticl": {
      "serverRank": 663369,
      "playerRank": 663369,
      "serverRankChange": -3273,
      "playerRankChange": -3273,
      "servers": 1,
      "players": 0
    },
    "mnr_zones": {
      "serverRank": 257084,
      "playerRank": 426509,
      "serverRankChange": -1463,
      "playerRankChange": -18117,
      "servers": 2,
      "players": 0
    },
    "mnr_consumables": {
      "serverRank": 663374,
      "playerRank": 663374,
      "serverRankChange": -3271,
      "playerRankChange": -3271,
      "servers": 1,
      "players": 0
    },
    "mnr_dispatch": {
      "serverRank": 257083,
      "playerRank": 426508,
      "serverRankChange": -1466,
      "playerRankChange": -18120,
      "servers": 2,
      "players": 0
    },
    "mnr_loadingscreen": {
      "serverRank": 663376,
      "playerRank": 663376,
      "serverRankChange": -407758,
      "playerRankChange": -254987,
      "servers": 1,
      "players": 0
    },
    "mnr_minimap": {
      "serverRank": 15589,
      "playerRank": 17941,
      "serverRankChange": 327,
      "playerRankChange": 24745,
      "servers": 33,
      "players": 381
    }
  }
}