{
  "success": true,
  "lastUpdated": 1783278051303,
  "totalServers": 24276,
  "totalPlayers": 172630,
  "resources": {
    "mnr_cayo": {
      "serverRank": 453,
      "playerRank": 644,
      "serverRankChange": -2,
      "playerRankChange": 1,
      "servers": 985,
      "players": 7190
    },
    "mnr_postals": {
      "serverRank": 4633,
      "playerRank": 17165,
      "serverRankChange": -21,
      "playerRankChange": -1471,
      "servers": 125,
      "players": 460
    },
    "mnr_sitanywhere": {
      "serverRank": 7653,
      "playerRank": 13517,
      "serverRankChange": 102,
      "playerRankChange": 4065,
      "servers": 76,
      "players": 574
    },
    "mnr_fuel": {
      "serverRank": 34199,
      "playerRank": 135080,
      "serverRankChange": 44,
      "playerRankChange": -52741,
      "servers": 16,
      "players": 31
    },
    "mnr_elevators": {
      "serverRank": 19374,
      "playerRank": 92500,
      "serverRankChange": 333,
      "playerRankChange": 2909,
      "servers": 30,
      "players": 65
    },
    "mnr_blips": {
      "serverRank": 110944,
      "playerRank": 424465,
      "serverRankChange": -3838,
      "playerRankChange": -127369,
      "servers": 4,
      "players": 0
    },
    "mnr_showid": {
      "serverRank": 130335,
      "playerRank": 210718,
      "serverRankChange": -7044,
      "playerRankChange": -103122,
      "servers": 3,
      "players": 9
    },
    "mnr_ipl": {
      "serverRank": 138281,
      "playerRank": 303510,
      "serverRankChange": -5670,
      "playerRankChange": -77994,
      "servers": 3,
      "players": 2
    },
    "mnr_anticl": {
      "serverRank": 713051,
      "playerRank": 713051,
      "serverRankChange": -8559,
      "playerRankChange": -8559,
      "servers": 1,
      "players": 0
    },
    "mnr_zones": {
      "serverRank": 274275,
      "playerRank": 464291,
      "serverRankChange": -1890,
      "playerRankChange": -34255,
      "servers": 2,
      "players": 0
    },
    "mnr_consumables": {
      "serverRank": 713057,
      "playerRank": 713057,
      "serverRankChange": -8558,
      "playerRankChange": -8558,
      "servers": 1,
      "players": 0
    },
    "mnr_dispatch": {
      "serverRank": 149729,
      "playerRank": 432671,
      "serverRankChange": 122654,
      "playerRankChange": -2637,
      "servers": 3,
      "players": 0
    },
    "mnr_loadingscreen": {
      "serverRank": 274274,
      "playerRank": 464290,
      "serverRankChange": -1890,
      "playerRankChange": -34255,
      "servers": 2,
      "players": 0
    },
    "mnr_minimap": {
      "serverRank": 15551,
      "playerRank": 17894,
      "serverRankChange": 634,
      "playerRankChange": 1641,
      "servers": 37,
      "players": 437
    }
  }
}