{
  "success": true,
  "lastUpdated": 1768093225901,
  "totalServers": 48106,
  "totalPlayers": 211858,
  "resources": {
    "mnr_cayo": {
      "serverRank": 862,
      "playerRank": 1525,
      "serverRankChange": 0,
      "playerRankChange": 86,
      "servers": 990,
      "players": 5079
    },
    "mnr_postals": {
      "serverRank": 5491,
      "playerRank": 11203,
      "serverRankChange": -35,
      "playerRankChange": 413,
      "servers": 201,
      "players": 832
    },
    "mnr_sitanywhere": {
      "serverRank": 14752,
      "playerRank": 19857,
      "serverRankChange": 47,
      "playerRankChange": -2274,
      "servers": 79,
      "players": 476
    },
    "mnr_fuel": {
      "serverRank": 29575,
      "playerRank": 47658,
      "serverRankChange": 54,
      "playerRankChange": -13305,
      "servers": 37,
      "players": 217
    },
    "mnr_elevators": {
      "serverRank": 27207,
      "playerRank": 93024,
      "serverRankChange": 139,
      "playerRankChange": 30845,
      "servers": 41,
      "players": 100
    },
    "mnr_blips": {
      "serverRank": 49556,
      "playerRank": 141501,
      "serverRankChange": -1513,
      "playerRankChange": 38281,
      "servers": 20,
      "players": 52
    },
    "mnr_showid": {
      "serverRank": 115011,
      "playerRank": 118061,
      "serverRankChange": 878,
      "playerRankChange": 26214,
      "servers": 6,
      "players": 70
    },
    "mnr_ipl": {
      "serverRank": 90052,
      "playerRank": 275609,
      "serverRankChange": -193,
      "playerRankChange": -32445,
      "servers": 9,
      "players": 11
    },
    "mnr_anticl": {
      "serverRank": 117516,
      "playerRank": 235345,
      "serverRankChange": 125,
      "playerRankChange": -11402,
      "servers": 6,
      "players": 18
    },
    "mnr_zones": {
      "serverRank": 137437,
      "playerRank": 365069,
      "serverRankChange": 5607,
      "playerRankChange": 145410,
      "servers": 5,
      "players": 4
    },
    "mnr_consumables": {
      "serverRank": 235700,
      "playerRank": 667289,
      "serverRankChange": 1584,
      "playerRankChange": 22718,
      "servers": 3,
      "players": 0
    },
    "mnr_dispatch": {
      "serverRank": 1045370,
      "playerRank": 1045370,
      "serverRankChange": 10525,
      "playerRankChange": 10525,
      "servers": 1,
      "players": 0
    },
    "mnr_loadingscreen": {
      "serverRank": 1045373,
      "playerRank": 1045373,
      "serverRankChange": 10525,
      "playerRankChange": 10525,
      "servers": 1,
      "players": 0
    }
  }
}