{
  "success": true,
  "lastUpdated": 1781895656809,
  "totalServers": 36079,
  "totalPlayers": 189870,
  "resources": {
    "mnr_cayo": {
      "serverRank": 463,
      "playerRank": 571,
      "serverRankChange": -7,
      "playerRankChange": 128,
      "servers": 1249,
      "players": 7788
    },
    "mnr_postals": {
      "serverRank": 4630,
      "playerRank": 18434,
      "serverRankChange": -26,
      "playerRankChange": -2014,
      "servers": 166,
      "players": 501
    },
    "mnr_sitanywhere": {
      "serverRank": 8212,
      "playerRank": 13344,
      "serverRankChange": 256,
      "playerRankChange": 8684,
      "servers": 94,
      "players": 655
    },
    "mnr_fuel": {
      "serverRank": 41745,
      "playerRank": 46637,
      "serverRankChange": 474,
      "playerRankChange": 23361,
      "servers": 17,
      "players": 178
    },
    "mnr_elevators": {
      "serverRank": 21367,
      "playerRank": 119337,
      "serverRankChange": 894,
      "playerRankChange": -14022,
      "servers": 37,
      "players": 47
    },
    "mnr_blips": {
      "serverRank": 129572,
      "playerRank": 332914,
      "serverRankChange": 8141,
      "playerRankChange": 113373,
      "servers": 4,
      "players": 2
    },
    "mnr_showid": {
      "serverRank": 174226,
      "playerRank": 380691,
      "serverRankChange": -23988,
      "playerRankChange": -276154,
      "servers": 3,
      "players": 1
    },
    "mnr_ipl": {
      "serverRank": 113635,
      "playerRank": 485654,
      "serverRankChange": 817,
      "playerRankChange": -45915,
      "servers": 5,
      "players": 0
    },
    "mnr_anticl": {
      "serverRank": 862806,
      "playerRank": 862806,
      "serverRankChange": -7324,
      "playerRankChange": -7324,
      "servers": 1,
      "players": 0
    },
    "mnr_zones": {
      "serverRank": 338935,
      "playerRank": 546393,
      "serverRankChange": -1948,
      "playerRankChange": -31420,
      "servers": 2,
      "players": 0
    },
    "mnr_consumables": {
      "serverRank": 862811,
      "playerRank": 862811,
      "serverRankChange": -7323,
      "playerRankChange": -7323,
      "servers": 1,
      "players": 0
    },
    "mnr_dispatch": {
      "serverRank": 185332,
      "playerRank": 501863,
      "serverRankChange": 151652,
      "playerRankChange": 13107,
      "servers": 3,
      "players": 0
    },
    "mnr_loadingscreen": {
      "serverRank": 862813,
      "playerRank": 862813,
      "serverRankChange": -525828,
      "playerRankChange": -347842,
      "servers": 1,
      "players": 0
    },
    "mnr_minimap": {
      "serverRank": 20592,
      "playerRank": 26291,
      "serverRankChange": -206,
      "playerRankChange": 3569,
      "servers": 38,
      "players": 350
    }
  }
}