{
  "success": true,
  "lastUpdated": 1779112844361,
  "totalServers": 41414,
  "totalPlayers": 145019,
  "resources": {
    "mnr_cayo": {
      "serverRank": 480,
      "playerRank": 500,
      "serverRankChange": 2,
      "playerRankChange": 296,
      "servers": 1285,
      "players": 6429
    },
    "mnr_postals": {
      "serverRank": 4746,
      "playerRank": 13482,
      "serverRankChange": 39,
      "playerRankChange": -2717,
      "servers": 171,
      "players": 501
    },
    "mnr_sitanywhere": {
      "serverRank": 9529,
      "playerRank": 29218,
      "serverRankChange": 222,
      "playerRankChange": -7749,
      "servers": 88,
      "players": 237
    },
    "mnr_fuel": {
      "serverRank": 34944,
      "playerRank": 53153,
      "serverRankChange": 2266,
      "playerRankChange": 39359,
      "servers": 22,
      "players": 120
    },
    "mnr_elevators": {
      "serverRank": 20848,
      "playerRank": 40994,
      "serverRankChange": 965,
      "playerRankChange": 50829,
      "servers": 40,
      "players": 167
    },
    "mnr_blips": {
      "serverRank": 111892,
      "playerRank": 286015,
      "serverRankChange": -1735,
      "playerRankChange": -76359,
      "servers": 5,
      "players": 2
    },
    "mnr_showid": {
      "serverRank": 130799,
      "playerRank": 262259,
      "serverRankChange": -4956,
      "playerRankChange": -137825,
      "servers": 4,
      "players": 3
    },
    "mnr_ipl": {
      "serverRank": 101813,
      "playerRank": 441342,
      "serverRankChange": -1092,
      "playerRankChange": -97872,
      "servers": 6,
      "players": 0
    },
    "mnr_anticl": {
      "serverRank": 866327,
      "playerRank": 866327,
      "serverRankChange": 4512,
      "playerRankChange": 4512,
      "servers": 1,
      "players": 0
    },
    "mnr_zones": {
      "serverRank": 345741,
      "playerRank": 521594,
      "serverRankChange": 851,
      "playerRankChange": 4335,
      "servers": 2,
      "players": 0
    },
    "mnr_consumables": {
      "serverRank": 866333,
      "playerRank": 866333,
      "serverRankChange": 4512,
      "playerRankChange": 4512,
      "servers": 1,
      "players": 0
    },
    "mnr_dispatch": {
      "serverRank": 345738,
      "playerRank": 521591,
      "serverRankChange": 852,
      "playerRankChange": 4336,
      "servers": 2,
      "players": 0
    },
    "mnr_loadingscreen": {
      "serverRank": 866336,
      "playerRank": 866336,
      "serverRankChange": 4512,
      "playerRankChange": 4512,
      "servers": 1,
      "players": 0
    },
    "mnr_minimap": {
      "serverRank": 18416,
      "playerRank": 96434,
      "serverRankChange": 169,
      "playerRankChange": -57893,
      "servers": 46,
      "players": 48
    }
  }
}