{
  "success": true,
  "lastUpdated": 1779206415619,
  "totalServers": 41116,
  "totalPlayers": 177295,
  "resources": {
    "mnr_cayo": {
      "serverRank": 478,
      "playerRank": 529,
      "serverRankChange": -3,
      "playerRankChange": 335,
      "servers": 1291,
      "players": 7552
    },
    "mnr_postals": {
      "serverRank": 4708,
      "playerRank": 14567,
      "serverRankChange": -41,
      "playerRankChange": -2171,
      "servers": 172,
      "players": 551
    },
    "mnr_sitanywhere": {
      "serverRank": 10148,
      "playerRank": 27218,
      "serverRankChange": -318,
      "playerRankChange": 2916,
      "servers": 82,
      "players": 309
    },
    "mnr_fuel": {
      "serverRank": 37949,
      "playerRank": 58053,
      "serverRankChange": -2508,
      "playerRankChange": 24569,
      "servers": 20,
      "players": 131
    },
    "mnr_elevators": {
      "serverRank": 21722,
      "playerRank": 51692,
      "serverRankChange": -1061,
      "playerRankChange": 56729,
      "servers": 38,
      "players": 151
    },
    "mnr_blips": {
      "serverRank": 131599,
      "playerRank": 284618,
      "serverRankChange": -20148,
      "playerRankChange": -40477,
      "servers": 4,
      "players": 3
    },
    "mnr_showid": {
      "serverRank": 131600,
      "playerRank": 284619,
      "serverRankChange": -5435,
      "playerRankChange": -158811,
      "servers": 4,
      "players": 3
    },
    "mnr_ipl": {
      "serverRank": 112803,
      "playerRank": 311519,
      "serverRankChange": -10293,
      "playerRankChange": 132091,
      "servers": 5,
      "players": 2
    },
    "mnr_anticl": {
      "serverRank": 873981,
      "playerRank": 873981,
      "serverRankChange": -5138,
      "playerRankChange": -5138,
      "servers": 1,
      "players": 0
    },
    "mnr_zones": {
      "serverRank": 348266,
      "playerRank": 542517,
      "serverRankChange": -1921,
      "playerRankChange": -18614,
      "servers": 2,
      "players": 0
    },
    "mnr_consumables": {
      "serverRank": 873986,
      "playerRank": 873986,
      "serverRankChange": -5138,
      "playerRankChange": -5138,
      "servers": 1,
      "players": 0
    },
    "mnr_dispatch": {
      "serverRank": 348264,
      "playerRank": 542515,
      "serverRankChange": -1920,
      "playerRankChange": -18613,
      "servers": 2,
      "players": 0
    },
    "mnr_loadingscreen": {
      "serverRank": 873989,
      "playerRank": 873989,
      "serverRankChange": -5138,
      "playerRankChange": -5138,
      "servers": 1,
      "players": 0
    },
    "mnr_minimap": {
      "serverRank": 19989,
      "playerRank": 88519,
      "serverRankChange": -683,
      "playerRankChange": -43821,
      "servers": 42,
      "players": 70
    }
  }
}