{
  "success": true,
  "lastUpdated": 1768014030266,
  "totalServers": 47376,
  "totalPlayers": 175720,
  "resources": {
    "mnr_cayo": {
      "serverRank": 870,
      "playerRank": 1653,
      "serverRankChange": 3,
      "playerRankChange": 125,
      "servers": 975,
      "players": 4057
    },
    "mnr_postals": {
      "serverRank": 5423,
      "playerRank": 10828,
      "serverRankChange": 50,
      "playerRankChange": 756,
      "servers": 200,
      "players": 742
    },
    "mnr_sitanywhere": {
      "serverRank": 15478,
      "playerRank": 27386,
      "serverRankChange": 25,
      "playerRankChange": -11672,
      "servers": 74,
      "players": 315
    },
    "mnr_fuel": {
      "serverRank": 30768,
      "playerRank": 72724,
      "serverRankChange": -70,
      "playerRankChange": -41193,
      "servers": 35,
      "players": 112
    },
    "mnr_elevators": {
      "serverRank": 28713,
      "playerRank": 81399,
      "serverRankChange": 247,
      "playerRankChange": 57020,
      "servers": 38,
      "players": 98
    },
    "mnr_blips": {
      "serverRank": 49246,
      "playerRank": 134641,
      "serverRankChange": 454,
      "playerRankChange": 68363,
      "servers": 20,
      "players": 46
    },
    "mnr_showid": {
      "serverRank": 113824,
      "playerRank": 90283,
      "serverRankChange": 1416,
      "playerRankChange": 58746,
      "servers": 6,
      "players": 84
    },
    "mnr_ipl": {
      "serverRank": 89204,
      "playerRank": 256787,
      "serverRankChange": 1559,
      "playerRankChange": 92180,
      "servers": 9,
      "players": 10
    },
    "mnr_anticl": {
      "serverRank": 117362,
      "playerRank": 235792,
      "serverRankChange": 2109,
      "playerRankChange": 84920,
      "servers": 6,
      "players": 13
    },
    "mnr_zones": {
      "serverRank": 143260,
      "playerRank": 603591,
      "serverRankChange": -1644,
      "playerRankChange": -113301,
      "servers": 5,
      "players": 0
    },
    "mnr_consumables": {
      "serverRank": 232924,
      "playerRank": 621477,
      "serverRankChange": 2852,
      "playerRankChange": 49065,
      "servers": 3,
      "players": 0
    },
    "mnr_dispatch": {
      "serverRank": 1022723,
      "playerRank": 1022723,
      "serverRankChange": 19122,
      "playerRankChange": 19122,
      "servers": 1,
      "players": 0
    },
    "mnr_loadingscreen": {
      "serverRank": 1022727,
      "playerRank": 1022727,
      "serverRankChange": 19121,
      "playerRankChange": 19121,
      "servers": 1,
      "players": 0
    }
  }
}