{
  "success": true,
  "lastUpdated": 1768665636489,
  "totalServers": 48246,
  "totalPlayers": 199200,
  "resources": {
    "mnr_cayo": {
      "serverRank": 894,
      "playerRank": 1384,
      "serverRankChange": -8,
      "playerRankChange": 190,
      "servers": 961,
      "players": 4488
    },
    "mnr_postals": {
      "serverRank": 5770,
      "playerRank": 18518,
      "serverRankChange": -120,
      "playerRankChange": -5658,
      "servers": 192,
      "players": 568
    },
    "mnr_sitanywhere": {
      "serverRank": 14919,
      "playerRank": 30349,
      "serverRankChange": 138,
      "playerRankChange": -14870,
      "servers": 78,
      "players": 352
    },
    "mnr_fuel": {
      "serverRank": 28230,
      "playerRank": 55439,
      "serverRankChange": 218,
      "playerRankChange": -19709,
      "servers": 39,
      "players": 174
    },
    "mnr_elevators": {
      "serverRank": 27053,
      "playerRank": 53515,
      "serverRankChange": 973,
      "playerRankChange": 56028,
      "servers": 41,
      "players": 185
    },
    "mnr_blips": {
      "serverRank": 47613,
      "playerRank": 181102,
      "serverRankChange": 1293,
      "playerRankChange": -26379,
      "servers": 21,
      "players": 28
    },
    "mnr_showid": {
      "serverRank": 132962,
      "playerRank": 243344,
      "serverRankChange": -4241,
      "playerRankChange": -104367,
      "servers": 5,
      "players": 13
    },
    "mnr_ipl": {
      "serverRank": 82639,
      "playerRank": 254514,
      "serverRankChange": 6684,
      "playerRankChange": 64987,
      "servers": 10,
      "players": 11
    },
    "mnr_anticl": {
      "serverRank": 118221,
      "playerRank": 273152,
      "serverRankChange": -2348,
      "playerRankChange": -38203,
      "servers": 6,
      "players": 9
    },
    "mnr_zones": {
      "serverRank": 141366,
      "playerRank": 468404,
      "serverRankChange": -6202,
      "playerRankChange": -133386,
      "servers": 5,
      "players": 1
    },
    "mnr_consumables": {
      "serverRank": 423623,
      "playerRank": 707989,
      "serverRankChange": -3783,
      "playerRankChange": 1883,
      "servers": 2,
      "players": 0
    },
    "mnr_dispatch": {
      "serverRank": 1048872,
      "playerRank": 1048872,
      "serverRankChange": -5885,
      "playerRankChange": -5885,
      "servers": 1,
      "players": 0
    },
    "mnr_loadingscreen": {
      "serverRank": 1048875,
      "playerRank": 1048875,
      "serverRankChange": -5886,
      "playerRankChange": -5886,
      "servers": 1,
      "players": 0
    }
  }
}