{
  "success": true,
  "lastUpdated": 1776477649773,
  "totalServers": 42133,
  "totalPlayers": 167735,
  "resources": {
    "mnr_cayo": {
      "serverRank": 540,
      "playerRank": 1001,
      "serverRankChange": 0,
      "playerRankChange": -184,
      "servers": 1197,
      "players": 5398
    },
    "mnr_postals": {
      "serverRank": 4399,
      "playerRank": 10677,
      "serverRankChange": 3,
      "playerRankChange": 387,
      "servers": 185,
      "players": 663
    },
    "mnr_sitanywhere": {
      "serverRank": 9913,
      "playerRank": 30167,
      "serverRankChange": 125,
      "playerRankChange": -16403,
      "servers": 86,
      "players": 250
    },
    "mnr_fuel": {
      "serverRank": 28271,
      "playerRank": 133098,
      "serverRankChange": -193,
      "playerRankChange": -99226,
      "servers": 29,
      "players": 29
    },
    "mnr_elevators": {
      "serverRank": 18227,
      "playerRank": 93850,
      "serverRankChange": -244,
      "playerRankChange": 8398,
      "servers": 47,
      "players": 56
    },
    "mnr_blips": {
      "serverRank": 131753,
      "playerRank": 274327,
      "serverRankChange": 217,
      "playerRankChange": 3742,
      "servers": 4,
      "players": 4
    },
    "mnr_showid": {
      "serverRank": 123888,
      "playerRank": 92937,
      "serverRankChange": 2053,
      "playerRankChange": 43335,
      "servers": 4,
      "players": 57
    },
    "mnr_ipl": {
      "serverRank": 81727,
      "playerRank": 437209,
      "serverRankChange": -3173,
      "playerRankChange": -225909,
      "servers": 8,
      "players": 0
    },
    "mnr_anticl": {
      "serverRank": 141229,
      "playerRank": 450089,
      "serverRankChange": -11413,
      "playerRankChange": -221944,
      "servers": 4,
      "players": 0
    },
    "mnr_zones": {
      "serverRank": 850983,
      "playerRank": 850983,
      "serverRankChange": 19085,
      "playerRankChange": 19085,
      "servers": 1,
      "players": 0
    },
    "mnr_consumables": {
      "serverRank": 850971,
      "playerRank": 850971,
      "serverRankChange": 19086,
      "playerRankChange": 19086,
      "servers": 1,
      "players": 0
    },
    "mnr_dispatch": {
      "serverRank": 850973,
      "playerRank": 850973,
      "serverRankChange": 19086,
      "playerRankChange": 19086,
      "servers": 1,
      "players": 0
    },
    "mnr_loadingscreen": {
      "serverRank": 850975,
      "playerRank": 850975,
      "serverRankChange": 19086,
      "playerRankChange": 19086,
      "servers": 1,
      "players": 0
    },
    "mnr_minimap": {
      "serverRank": 23606,
      "playerRank": 29373,
      "serverRankChange": -971,
      "playerRankChange": 12678,
      "servers": 35,
      "players": 257
    }
  }
}