{
  "success": true,
  "lastUpdated": 1778263256391,
  "totalServers": 40478,
  "totalPlayers": 195989,
  "resources": {
    "mnr_cayo": {
      "serverRank": 491,
      "playerRank": 556,
      "serverRankChange": -5,
      "playerRankChange": 114,
      "servers": 1259,
      "players": 8259
    },
    "mnr_postals": {
      "serverRank": 4566,
      "playerRank": 17139,
      "serverRankChange": -71,
      "playerRankChange": -4315,
      "servers": 177,
      "players": 514
    },
    "mnr_sitanywhere": {
      "serverRank": 9507,
      "playerRank": 28883,
      "serverRankChange": -487,
      "playerRankChange": -14341,
      "servers": 88,
      "players": 312
    },
    "mnr_fuel": {
      "serverRank": 39835,
      "playerRank": 79607,
      "serverRankChange": -1837,
      "playerRankChange": -45319,
      "servers": 19,
      "players": 93
    },
    "mnr_elevators": {
      "serverRank": 22987,
      "playerRank": 81923,
      "serverRankChange": 142,
      "playerRankChange": 24655,
      "servers": 36,
      "players": 89
    },
    "mnr_blips": {
      "serverRank": 173715,
      "playerRank": 333930,
      "serverRankChange": -37174,
      "playerRankChange": 50026,
      "servers": 3,
      "players": 2
    },
    "mnr_showid": {
      "serverRank": 249471,
      "playerRank": 194095,
      "serverRankChange": -70405,
      "playerRankChange": 194132,
      "servers": 2,
      "players": 15
    },
    "mnr_ipl": {
      "serverRank": 88029,
      "playerRank": 327921,
      "serverRankChange": -1333,
      "playerRankChange": -86499,
      "servers": 7,
      "players": 2
    },
    "mnr_anticl": {
      "serverRank": 866144,
      "playerRank": 866144,
      "serverRankChange": -932,
      "playerRankChange": -932,
      "servers": 1,
      "players": 0
    },
    "mnr_zones": {
      "serverRank": 866159,
      "playerRank": 866159,
      "serverRankChange": -932,
      "playerRankChange": -932,
      "servers": 1,
      "players": 0
    },
    "mnr_consumables": {
      "serverRank": 866149,
      "playerRank": 866149,
      "serverRankChange": -933,
      "playerRankChange": -933,
      "servers": 1,
      "players": 0
    },
    "mnr_dispatch": {
      "serverRank": 345076,
      "playerRank": 552410,
      "serverRankChange": 291,
      "playerRankChange": -4871,
      "servers": 2,
      "players": 0
    },
    "mnr_loadingscreen": {
      "serverRank": 866152,
      "playerRank": 866152,
      "serverRankChange": -933,
      "playerRankChange": -933,
      "servers": 1,
      "players": 0
    },
    "mnr_minimap": {
      "serverRank": 21939,
      "playerRank": 104844,
      "serverRankChange": -561,
      "playerRankChange": -26984,
      "servers": 38,
      "players": 57
    }
  }
}