{
  "success": true,
  "lastUpdated": 1766865617650,
  "totalServers": 45706,
  "totalPlayers": 215662,
  "resources": {
    "mnr_cayo": {
      "serverRank": 965,
      "playerRank": 1948,
      "serverRankChange": 10,
      "playerRankChange": -39,
      "servers": 840,
      "players": 3813
    },
    "mnr_postals": {
      "serverRank": 5558,
      "playerRank": 16767,
      "serverRankChange": -49,
      "playerRankChange": -4849,
      "servers": 182,
      "players": 620
    },
    "mnr_sitanywhere": {
      "serverRank": 13281,
      "playerRank": 23667,
      "serverRankChange": 420,
      "playerRankChange": -6168,
      "servers": 80,
      "players": 454
    },
    "mnr_fuel": {
      "serverRank": 26638,
      "playerRank": 57888,
      "serverRankChange": -131,
      "playerRankChange": -12941,
      "servers": 38,
      "players": 183
    },
    "mnr_elevators": {
      "serverRank": 28898,
      "playerRank": 121792,
      "serverRankChange": -46,
      "playerRankChange": -2181,
      "servers": 35,
      "players": 66
    },
    "mnr_blips": {
      "serverRank": 47941,
      "playerRank": 127273,
      "serverRankChange": 3256,
      "playerRankChange": 42928,
      "servers": 19,
      "players": 60
    },
    "mnr_showid": {
      "serverRank": 122885,
      "playerRank": 180098,
      "serverRankChange": -17268,
      "playerRankChange": -60250,
      "servers": 5,
      "players": 30
    },
    "mnr_ipl": {
      "serverRank": 100371,
      "playerRank": 281217,
      "serverRankChange": -1253,
      "playerRankChange": 25649,
      "servers": 7,
      "players": 9
    },
    "mnr_anticl": {
      "serverRank": 148151,
      "playerRank": 291763,
      "serverRankChange": 21,
      "playerRankChange": 48972,
      "servers": 4,
      "players": 8
    },
    "mnr_zones": {
      "serverRank": 126750,
      "playerRank": 301763,
      "serverRankChange": -1643,
      "playerRankChange": 20542,
      "servers": 5,
      "players": 7
    },
    "mnr_consumables": {
      "serverRank": 398769,
      "playerRank": 673565,
      "serverRankChange": -10762,
      "playerRankChange": -23692,
      "servers": 2,
      "players": 0
    }
  }
}