{
  "success": true,
  "lastUpdated": 1779645639581,
  "totalServers": 40157,
  "totalPlayers": 205708,
  "resources": {
    "mnr_cayo": {
      "serverRank": 492,
      "playerRank": 610,
      "serverRankChange": 1,
      "playerRankChange": 196,
      "servers": 1247,
      "players": 8176
    },
    "mnr_postals": {
      "serverRank": 4736,
      "playerRank": 17771,
      "serverRankChange": -109,
      "playerRankChange": -6696,
      "servers": 170,
      "players": 517
    },
    "mnr_sitanywhere": {
      "serverRank": 9640,
      "playerRank": 38996,
      "serverRankChange": 30,
      "playerRankChange": -6010,
      "servers": 86,
      "players": 230
    },
    "mnr_fuel": {
      "serverRank": 38078,
      "playerRank": 75669,
      "serverRankChange": -365,
      "playerRankChange": -5471,
      "servers": 20,
      "players": 108
    },
    "mnr_elevators": {
      "serverRank": 22395,
      "playerRank": 113211,
      "serverRankChange": 958,
      "playerRankChange": 502,
      "servers": 37,
      "players": 58
    },
    "mnr_blips": {
      "serverRank": 116641,
      "playerRank": 509122,
      "serverRankChange": 47028,
      "playerRankChange": -270478,
      "servers": 5,
      "players": 0
    },
    "mnr_showid": {
      "serverRank": 127780,
      "playerRank": 233117,
      "serverRankChange": -3427,
      "playerRankChange": -76681,
      "servers": 4,
      "players": 10
    },
    "mnr_ipl": {
      "serverRank": 114054,
      "playerRank": 399236,
      "serverRankChange": -5067,
      "playerRankChange": -152426,
      "servers": 5,
      "players": 1
    },
    "mnr_anticl": {
      "serverRank": 879314,
      "playerRank": 879314,
      "serverRankChange": -18756,
      "playerRankChange": -18756,
      "servers": 1,
      "players": 0
    },
    "mnr_zones": {
      "serverRank": 346183,
      "playerRank": 568273,
      "serverRankChange": -6341,
      "playerRankChange": -39172,
      "servers": 2,
      "players": 0
    },
    "mnr_consumables": {
      "serverRank": 879319,
      "playerRank": 879319,
      "serverRankChange": -18754,
      "playerRankChange": -18754,
      "servers": 1,
      "players": 0
    },
    "mnr_dispatch": {
      "serverRank": 346182,
      "playerRank": 568272,
      "serverRankChange": -6343,
      "playerRankChange": -39174,
      "servers": 2,
      "players": 0
    },
    "mnr_loadingscreen": {
      "serverRank": 879322,
      "playerRank": 879322,
      "serverRankChange": -18754,
      "playerRankChange": -18754,
      "servers": 1,
      "players": 0
    },
    "mnr_minimap": {
      "serverRank": 20840,
      "playerRank": 86367,
      "serverRankChange": -719,
      "playerRankChange": -43356,
      "servers": 40,
      "players": 90
    }
  }
}