{
  "success": true,
  "lastUpdated": 1776474049774,
  "totalServers": 42201,
  "totalPlayers": 181551,
  "resources": {
    "mnr_cayo": {
      "serverRank": 538,
      "playerRank": 1010,
      "serverRankChange": 2,
      "playerRankChange": -193,
      "servers": 1199,
      "players": 5569
    },
    "mnr_postals": {
      "serverRank": 4401,
      "playerRank": 10744,
      "serverRankChange": 1,
      "playerRankChange": 320,
      "servers": 185,
      "players": 701
    },
    "mnr_sitanywhere": {
      "serverRank": 9929,
      "playerRank": 25858,
      "serverRankChange": 109,
      "playerRankChange": -12094,
      "servers": 86,
      "players": 302
    },
    "mnr_fuel": {
      "serverRank": 28222,
      "playerRank": 112948,
      "serverRankChange": -144,
      "playerRankChange": -79076,
      "servers": 29,
      "players": 46
    },
    "mnr_elevators": {
      "serverRank": 18262,
      "playerRank": 103563,
      "serverRankChange": -279,
      "playerRankChange": -1315,
      "servers": 47,
      "players": 53
    },
    "mnr_blips": {
      "serverRank": 132092,
      "playerRank": 282429,
      "serverRankChange": -122,
      "playerRankChange": -4360,
      "servers": 4,
      "players": 4
    },
    "mnr_showid": {
      "serverRank": 124614,
      "playerRank": 107584,
      "serverRankChange": 1327,
      "playerRankChange": 28688,
      "servers": 4,
      "players": 50
    },
    "mnr_ipl": {
      "serverRank": 80552,
      "playerRank": 326081,
      "serverRankChange": -1998,
      "playerRankChange": -114781,
      "servers": 8,
      "players": 2
    },
    "mnr_anticl": {
      "serverRank": 129851,
      "playerRank": 232245,
      "serverRankChange": -35,
      "playerRankChange": -4100,
      "servers": 4,
      "players": 8
    },
    "mnr_zones": {
      "serverRank": 854900,
      "playerRank": 854900,
      "serverRankChange": 15168,
      "playerRankChange": 15168,
      "servers": 1,
      "players": 0
    },
    "mnr_consumables": {
      "serverRank": 854889,
      "playerRank": 854889,
      "serverRankChange": 15168,
      "playerRankChange": 15168,
      "servers": 1,
      "players": 0
    },
    "mnr_dispatch": {
      "serverRank": 854891,
      "playerRank": 854891,
      "serverRankChange": 15168,
      "playerRankChange": 15168,
      "servers": 1,
      "players": 0
    },
    "mnr_loadingscreen": {
      "serverRank": 854893,
      "playerRank": 854893,
      "serverRankChange": 15168,
      "playerRankChange": 15168,
      "servers": 1,
      "players": 0
    },
    "mnr_minimap": {
      "serverRank": 23620,
      "playerRank": 29304,
      "serverRankChange": -985,
      "playerRankChange": 12747,
      "servers": 35,
      "players": 272
    }
  }
}